[{"name":"Cake franboise","quantity":"15","image":"/src/assets/patisserie/cake_framboise.png","choice":true,"id":"11"},{"name":"Eclairs au chocolat","quantity":"10","image":"/src/assets/patisserie/eclair.png","id":"13"},{"name":"Brioche","quantity":"12","image":"/src/assets/patisserie/brioche.png","id":"14"},{"name":"fondant chocolat","quantity":"11","image":"/src/assets/patisserie/fondant_chocolat.png","id":"15"},{"name":"Fondant Suprême","quantity":"16","image":"/src/assets/patisserie/fondant_supreme.png","id":"16"}]